i-2.1.0.dist-info/LICENSE.txt
i-2.1.0.dist-info/METADATA
i-2.1.0.dist-info/RECORD
i-2.1.0.dist-info/WHEEL
i-2.1.0.dist-info/top_level.txt
icecream/__init__.py
icecream/__version__.py
icecream/builtins.py
icecream/coloring.py
icecream/icecream.py
